<?xml version="1.0" encoding="UTF-8" ?>
<!DOCTYPE mapper PUBLIC "-//mybatis.org//DTD Mapper 3.0//EN" "http://mybatis.org/dtd/mybatis-3-mapper.dtd" >
<mapper namespace="com.woman.dao.companyMapper" >
  <resultMap id="BaseResultMap" type="com.woman.pojo.company" >
    <!--
      WARNING - @mbggenerated
      This element is automatically generated by MyBatis Generator, do not modify.
    -->
    <id column="companyId" property="companyid" jdbcType="INTEGER" />
    <result column="companyName" property="companyname" jdbcType="VARCHAR" />
    <result column="remarkName" property="remarkname" jdbcType="VARCHAR" />
    <result column="enterpriseType" property="enterprisetype" jdbcType="VARCHAR" />
    <result column="registeredCapital" property="registeredcapital" jdbcType="INTEGER" />
    <result column="businessScope" property="businessscope" jdbcType="VARCHAR" />
    <result column="companyType" property="companytype" jdbcType="VARCHAR" />
    <result column="linkman" property="linkman" jdbcType="VARCHAR" />
    <result column="linkPhone" property="linkphone" jdbcType="VARCHAR" />
    <result column="createTime" property="createtime" jdbcType="VARCHAR" />
    <result column="openid" property="openid" jdbcType="VARCHAR" />
<!--     <association property="shareholder" javaType="com.woman.pojo.shareholder"> 
	    <id property="shareholderid" column="shareholderid" jdbcType="INTEGER" />	  
	    <id property="name" column="name" jdbcType="VARCHAR" />
	    <result property="phone" column="phone" jdbcType="VARCHAR" />
	    <result property="email" column="email" jdbcType="VARCHAR" />
	    <result property="holdscale" column="holdscale" jdbcType="VARCHAR" />
	    <result property="idcard" column="idcard" jdbcType="VARCHAR" />
	    <result property="idimgZ" column="idimgZ" jdbcType="VARCHAR" />
	    <result property="idimgF" column="idimgF" jdbcType="VARCHAR" />
        <result property="createtime" column="createtime" jdbcType="VARCHAR" />
     </association> -->
  </resultMap>
  <sql id="Base_Column_List" >
    <!--
      WARNING - @mbggenerated
      This element is automatically generated by MyBatis Generator, do not modify.
    -->
    companyId, companyName, remarkName, enterpriseType, registeredCapital, businessScope, 
    companyType, linkman, linkPhone, createTime, openid
  </sql>
  <select id="selectByPrimaryKey" resultMap="BaseResultMap" parameterType="java.lang.Integer" >
    <!--
      WARNING - @mbggenerated
      This element is automatically generated by MyBatis Generator, do not modify.
    -->
    select 
    <include refid="Base_Column_List" />
    from company
    where companyId = #{companyid,jdbcType=INTEGER}
  </select>
  <delete id="deleteByPrimaryKey" parameterType="java.lang.Integer" >
    <!--
      WARNING - @mbggenerated
      This element is automatically generated by MyBatis Generator, do not modify.
    -->
    delete from company
    where companyId = #{companyid,jdbcType=INTEGER}
  </delete>
   <!--  -->
  
  <!-- 增加公司 start -->
  <insert id="insert" parameterType="com.woman.pojo.company" useGeneratedKeys="true" keyProperty="companyid">
    <!--
      WARNING - @mbggenerated
      This element is automatically generated by MyBatis Generator, do not modify.
    -->       
    insert into company (companyName, remarkName, 
      enterpriseType, registeredCapital, businessScope, 
      companyType, linkman, linkPhone, 
      createTime, openid)
    values (#{companyname,jdbcType=VARCHAR}, #{remarkname,jdbcType=VARCHAR}, 
      #{enterprisetype,jdbcType=VARCHAR}, #{registeredcapital,jdbcType=INTEGER}, #{businessscope,jdbcType=VARCHAR}, 
      #{companytype,jdbcType=VARCHAR}, #{linkman,jdbcType=VARCHAR}, #{linkphone,jdbcType=VARCHAR}, 
      #{createtime,jdbcType=VARCHAR}, #{openid,jdbcType=VARCHAR})
  </insert>
  <!--增加公司 end  -->
  <insert id="insertSelective" parameterType="com.woman.pojo.company" >
    <!--
      WARNING - @mbggenerated
      This element is automatically generated by MyBatis Generator, do not modify.
    -->
    insert into company
    <trim prefix="(" suffix=")" suffixOverrides="," >
      <if test="companyid != null" >
        companyId,
      </if>
      <if test="companyname != null" >
        companyName,
      </if>
      <if test="remarkname != null" >
        remarkName,
      </if>
      <if test="enterprisetype != null" >
        enterpriseType,
      </if>
      <if test="registeredcapital != null" >
        registeredCapital,
      </if>
      <if test="businessscope != null" >
        businessScope,
      </if>
      <if test="companytype != null" >
        companyType,
      </if>
      <if test="linkman != null" >
        linkman,
      </if>
      <if test="linkphone != null" >
        linkPhone,
      </if>
      <if test="createtime != null" >
        createTime,
      </if>
      <if test="openid != null" >
        openid,
      </if>
    </trim>
    <trim prefix="values (" suffix=")" suffixOverrides="," >
      <if test="companyid != null" >
        #{companyid,jdbcType=INTEGER},
      </if>
      <if test="companyname != null" >
        #{companyname,jdbcType=VARCHAR},
      </if>
      <if test="remarkname != null" >
        #{remarkname,jdbcType=VARCHAR},
      </if>
      <if test="enterprisetype != null" >
        #{enterprisetype,jdbcType=VARCHAR},
      </if>
      <if test="registeredcapital != null" >
        #{registeredcapital,jdbcType=INTEGER},
      </if>
      <if test="businessscope != null" >
        #{businessscope,jdbcType=VARCHAR},
      </if>
      <if test="companytype != null" >
        #{companytype,jdbcType=VARCHAR},
      </if>
      <if test="linkman != null" >
        #{linkman,jdbcType=VARCHAR},
      </if>
      <if test="linkphone != null" >
        #{linkphone,jdbcType=VARCHAR},
      </if>
      <if test="createtime != null" >
        #{createtime,jdbcType=VARCHAR},
      </if>
      <if test="openid != null" >
        #{openid,jdbcType=VARCHAR},
      </if>
    </trim>
  </insert>
  <update id="updateByPrimaryKeySelective" parameterType="com.woman.pojo.company" >
    <!--
      WARNING - @mbggenerated
      This element is automatically generated by MyBatis Generator, do not modify.
    -->
    update company
    <set >
      <if test="companyname != null" >
        companyName = #{companyname,jdbcType=VARCHAR},
      </if>
      <if test="remarkname != null" >
        remarkName = #{remarkname,jdbcType=VARCHAR},
      </if>
      <if test="enterprisetype != null" >
        enterpriseType = #{enterprisetype,jdbcType=VARCHAR},
      </if>
      <if test="registeredcapital != null" >
        registeredCapital = #{registeredcapital,jdbcType=INTEGER},
      </if>
      <if test="businessscope != null" >
        businessScope = #{businessscope,jdbcType=VARCHAR},
      </if>
      <if test="companytype != null" >
        companyType = #{companytype,jdbcType=VARCHAR},
      </if>
      <if test="linkman != null" >
        linkman = #{linkman,jdbcType=VARCHAR},
      </if>
      <if test="linkphone != null" >
        linkPhone = #{linkphone,jdbcType=VARCHAR},
      </if>
      <if test="createtime != null" >
        createTime = #{createtime,jdbcType=VARCHAR},
      </if>
      <if test="openid != null" >
        openid = #{openid,jdbcType=VARCHAR},
      </if>
    </set>
    where companyId = #{companyid,jdbcType=INTEGER}
  </update>
  <update id="updateByPrimaryKey" parameterType="com.woman.pojo.company" >
    <!--
      WARNING - @mbggenerated
      This element is automatically generated by MyBatis Generator, do not modify.
    -->
    update company
    set companyName = #{companyname,jdbcType=VARCHAR},
      remarkName = #{remarkname,jdbcType=VARCHAR},
      enterpriseType = #{enterprisetype,jdbcType=VARCHAR},
      registeredCapital = #{registeredcapital,jdbcType=INTEGER},
      businessScope = #{businessscope,jdbcType=VARCHAR},
      companyType = #{companytype,jdbcType=VARCHAR},
      linkman = #{linkman,jdbcType=VARCHAR},
      linkPhone = #{linkphone,jdbcType=VARCHAR},
      createTime = #{createtime,jdbcType=VARCHAR},
      openid = #{openid,jdbcType=VARCHAR}
    where companyId = #{companyid,jdbcType=INTEGER}
  </update>
  
  
  
</mapper>